_qlip_algorithms_dummy_ext.cpython-311-x86_64-linux-gnu.so
qlip_algorithms/__init__.py
qlip_algorithms/version.py
qlip_algorithms/anna/__init__.py
qlip_algorithms/anna/algorithm.py
qlip_algorithms/anna/anna.py
qlip_algorithms/anna/bag_of_algorithms.py
qlip_algorithms/anna/dashboard.py
qlip_algorithms/anna/data_utils.py
qlip_algorithms/anna/utils.py
qlip_algorithms/metrics/__init__.py
qlip_algorithms/metrics/image_benchmark.py
qlip_algorithms/post_train/__init__.py
qlip_algorithms/post_train/bias_correction.py
qlip_algorithms/post_train/layerwise_distillation.py
qlip_algorithms/post_train/layerwise_utils.py
qlip_algorithms/pyarmor_runtime_008031/__init__.py
qlip_algorithms/pyarmor_runtime_008031/pyarmor_runtime.so
qlip_algorithms/quantization/__init__.py
qlip_algorithms/quantization/lsq.py
qlip_algorithms/quantization/post_training_quantization.py
qlip_algorithms/quantization/qsin.py
qlip_algorithms/quantization/qsin_backward.py
qlip_algorithms/quantization/qsin_forward.py
qlip_algorithms/quantization/smooth_quant.py
qlip_algorithms-0.1.1.dist-info/METADATA
qlip_algorithms-0.1.1.dist-info/WHEEL
qlip_algorithms-0.1.1.dist-info/entry_points.txt
qlip_algorithms-0.1.1.dist-info/top_level.txt
qlip_algorithms-0.1.1.dist-info/RECORD
qlip_algorithms-0.1.1.dist-info/licenses/LICENSE
