Metadata-Version: 2.4
Name: qlip.algorithms
Version: 0.1.1
Summary: Library with neural networks compression and acceleration algorithms built on QLIP.
Author-email: TheStage AI team <hello@thestage.ai>
Classifier: Programming Language :: Python :: 3.10
Classifier: Programming Language :: Python :: 3.11
Classifier: Programming Language :: Python :: 3.12
Requires-Python: >=3.10
License-File: LICENSE
Requires-Dist: requests
Requires-Dist: numpy
Requires-Dist: torch
Requires-Dist: tqdm
Requires-Dist: streamlit
Requires-Dist: pandas
Requires-Dist: streamlit-image-comparison
Requires-Dist: pillow
Requires-Dist: plotly
Dynamic: license-file
